fast_hbcc/__init__.py
fast_hbcc/hbcc.py
fast_hbcc/n_hop.py
fast_hbcc/priority_queue.py
fast_hbcc/sub_clusters.py
fast_hbcc/tests/__init__.py
fast_hbcc/tests/test_hbcc.py
fast_hbcc/tests/test_sub_clusters.py
fast_hbcc-0.1.0.dist-info/LICENSE
fast_hbcc-0.1.0.dist-info/METADATA
fast_hbcc-0.1.0.dist-info/WHEEL
fast_hbcc-0.1.0.dist-info/top_level.txt
fast_hbcc-0.1.0.dist-info/RECORD
