Metadata-Version: 2.2
Name: fast_hbcc
Version: 0.1.0
Summary: Hierarchical Boundary Coefficient Clustering.
Author-email: Jelmer Bot <jelmer.bot@uhasselt.be>
License: BSD-2-Clause
Project-URL: Homepage, https://github.com/vda-lab/fast_hbcc
Project-URL: Issues, https://github.com/vda-lab/fast_hbcc/issues
Keywords: clustering,machine learning
Classifier: Development Status :: 4 - Beta
Classifier: License :: OSI Approved :: BSD License
Classifier: Intended Audience :: Science/Research
Classifier: Topic :: Scientific/Engineering
Classifier: Topic :: Scientific/Engineering :: Visualization
Classifier: Natural Language :: English
Classifier: Operating System :: OS Independent
Classifier: Programming Language :: Python :: 3 :: Only
Requires-Python: >=3.10
License-File: LICENSE
Requires-Dist: numpy<3,>=1.2
Requires-Dist: numba>=0.57.1
Requires-Dist: scipy>=1.9
Requires-Dist: scikit-learn>=1.1
Requires-Dist: fast_hdbscan>=0.2.1
Provides-Extra: tests
Requires-Dist: pytest; extra == "tests"
Provides-Extra: docs
Requires-Dist: sphinx>=8; extra == "docs"
Requires-Dist: nbsphinx>=0.9; extra == "docs"
Requires-Dist: sphinx_rtd_theme>=2.0; extra == "docs"
Requires-Dist: matplotlib>=3.8; extra == "docs"
Requires-Dist: pygments>=2.4.1; extra == "docs"
Requires-Dist: jupyterlab_pygments>=0.1.1; extra == "docs"
Requires-Dist: ipykernel; extra == "docs"
Requires-Dist: numpydoc; extra == "docs"
Provides-Extra: notebooks
Requires-Dist: pandas>=2.2; extra == "notebooks"
Requires-Dist: jupyterlab>=4; extra == "notebooks"
Requires-Dist: matplotlib>=3.4; extra == "notebooks"
Requires-Dist: tqdm>=4.62.3; extra == "notebooks"
